full_mcp_server/__init__.py
full_mcp_server/server.py
full_mcp_server-0.1.5.dist-info/METADATA
full_mcp_server-0.1.5.dist-info/WHEEL
full_mcp_server-0.1.5.dist-info/entry_points.txt
full_mcp_server-0.1.5.dist-info/RECORD
