Metadata-Version: 2.4
Name: full-mcp-server
Version: 0.1.5
Summary: Creating MCP project with theS SDK wizard
Author-email: Sakthivel Chellapparimanam <srcsakthivel@gmail.com>
Requires-Python: >=3.13
Requires-Dist: boto3>=1.38.5
Requires-Dist: mcp>=1.6.0
Requires-Dist: python-dotenv>=1.1.0
